ak_tool/__init__.py
ak_tool/cli.py
ak_tool/config.py
ak_tool/core.py
ak_tool/logger.py
ak_tool-0.1.5.dist-info/entry_points.txt
ak_tool-0.1.5.dist-info/LICENSE.md
ak_tool-0.1.5.dist-info/WHEEL
ak_tool-0.1.5.dist-info/METADATA
ak_tool-0.1.5.dist-info/RECORD
