Metadata-Version: 2.3
Name: ak-tool
Version: 0.1.5
Summary: Consolidates AWS MFA login, Kubernetes context switching, and Kubernetes API token refreshing into one simple CLI tool.
Author-email: Aharon Haravon <aharon.haravon@gmail.com>
Requires-Python: >=3.7
Classifier: Programming Language :: Python :: 3
Classifier: License :: OSI Approved :: MIT License
Classifier: Operating System :: OS Independent
Requires-Dist: boto3
Requires-Dist: pyyaml
Requires-Dist: pytest
Requires-Dist: requests
Requires-Dist: click >=8.1
Requires-Dist: python-crontab
Requires-Dist: flake8 ; extra == "dev"
Requires-Dist: black ; extra == "dev"
Requires-Dist: pytest-cov ; extra == "dev"
Requires-Dist: mypy ; extra == "dev"
Requires-Dist: flit ; extra == "dev"
Requires-Dist: sphinx ; extra == "dev"
Requires-Dist: docformatter ; extra == "dev"
Requires-Dist: bump2version ; extra == "dev"
Provides-Extra: dev
